Workbook

Sheet Cover
A1: RELIANCE INDUSTRIES LIMITED
A2: Financial Statement Analysis — FY2021 to FY2025
D4: Company | E4: Reliance Industries Limited
D5: Ticker | E5: NSE: RELIANCE / BSE: 500325
D6: Sector | E6: Oil & Gas, Telecom, Retail
D7: Currency | E7: Indian Rupees (₹ Crores)
D8: Period | E8: FY2021 — FY2025
D9: Data Source | E9: Screener.in
D10: Analyst | E10: Hardik Parmar
D11: Date | E11: 46082
A15: This model is built for educational and portfolio purposes only. Data sourced from publicly available financial statements via Screener.in

Sheet Income_Statement
A1: RELIANCE INDUSTRIES - INCOME STATEMENT
A2: All figures in ₹ Crores
A3: Particulars | B3: FY2021 | C3: FY2022 | D3: FY2023 | E3: FY2024 | F3: FY2025 | G3: 5Y CAGR
A4: REVENUE
A5: Revenue from Operations | B5: 466307 | C5: 694673 | D5: 876396 | E5: 899041 | F5: 962820 | G5: =(F5/B5)^(1/4)-1 -> 0.19872149
A6: Other Income | B6: 22432 | C6: 19600 | D6: 12020 | E6: 15792 | F6: 17824
A7: Total Revenue | B7: =B5+B6 -> 488739 | C7: =C5+C6 -> 714273 | D7: =D5+D6 -> 888416 | E7: =E5+E6 -> 914833 | F7: =F5+F6 -> 980644
A9: EXPENSES
A10: Operating Expenses | B10: 385517 | C10: 586092 | D10: 734078 | E10: 736543 | F10: 797222
A11: Interest | B11: 21189 | C11: 14584 | D11: 19571 | E11: 23118 | F11: 24269
A12: Depreciation | B12: 26572 | C12: 29782 | D12: 40303 | E12: 50832 | F12: 53136
A13: Tax | B13: 1722 | C13: 15970 | D13: 20376 | E13: 25707 | F13: 25230
A14: Total Expense | B14: =B10+B11+B12+B13 -> 435000 | C14: =C10+C11+C12+C13 -> 646428 | D14: =D10+D11+D12+D13 -> 814328 | E14: =E10+E11+E12+E13 -> 836200 | F14: =F10+F11+F12+F13 -> 899857
A16: PROFITABILITY
A17: EBIT (Operating Profit) | B17: =B5-B10 -> 80790 | C17: =C5-C10 -> 108581 | D17: =D5-D10 -> 142318 | E17: =E5-E10 -> 162498 | F17: =F5-F10 -> 165598 | G17: =(F17/B17)^(1/4)-1 -> 0.19653214
A18: EBITDA | B18: =B17+B12 -> 107362 | C18: =C17+C12 -> 138363 | D18: =D17+D12 -> 182621 | E18: =E17+E12 -> 213330 | F18: =F17+F12 -> 218734 | G18: =(F18/B18)^(1/4)-1 -> 0.1947208
A19: Profit Before Tax | B19: 55461 | C19: 83815 | D19: 94464 | E19: 104340 | F19: 106017
A20: Net Profit (PAT) | B20: 49128 | C20: 60705 | D20: 66702 | E20: 69621 | F20: 69648 | G20: =(F20/B20)^(1/4)-1 -> 0.091176216
A21: Earnings Per Share | B21: 38.747841 | C21: 44.867626 | D21: 49.294963 | E21: 51.451439 | F21: 51.467589 | G21: =(F21/B21)^(1/4)-1 -> 0.073548276
A23: MARGINS
A24: Operating Profit Margin % | B24: =B17/B5 -> 0.17325496 | C24: =C17/C5 -> 0.1563052 | D24: =D17/D5 -> 0.16239006 | E24: =E17/E5 -> 0.18074593 | F24: =F17/F5 -> 0.17199269
A25: Net Profit Margin % | B25: =B20/B7 -> 0.10051991 | C25: =C20/C7 -> 0.084988513 | D25: =D20/D7 -> 0.075079692 | E25: =E20/E7 -> 0.076102414 | F25: =F20/F7 -> 0.071022716
A26: Tax Rate % | B26: =B13/B19 -> 0.031048845 | C26: =C13/C19 -> 0.19053869 | D26: =D13/D19 -> 0.21570122 | E26: =E13/E19 -> 0.24637723 | F26: =F13/F19 -> 0.2379807
A28: MARKET DATA
A29: Price | B29: 918.78 | C29: 1208.51 | D29: 1069.21 | E29: 1485.85 | F29: 1275.1
A30: P/E Ratio | B30: =B29/B21 -> 23.711773 | C30: =C29/C21 -> 26.935011 | D30: =D29/D21 -> 21.690046 | E30: =E29/E21 -> 28.878687 | F30: =F29/F21 -> 24.774815
A31: Market Cap (₹ Cr) | B31: =B29*(1352) -> 1242190.6 | C31: =C29*(1352) -> 1633905.5 | D31: =D29*(1352) -> 1445571.9 | E31: =E29*(1352) -> 2008869.2 | F31: =F29*(1352) -> 1723935.2
A33: GROWTH RATES
A34: Sales Growth % | B34: - | C34: =(C5-B5)/B5 -> 0.48973316 | D34: =(D5-C5)/C5 -> 0.26159502 | E34: =(E5-D5)/D5 -> 0.025838776 | F34: =(F5-E5)/E5 -> 0.070941147
A35: Operating Profit Growth % | B35: - | C35: =(C17-B17)/B17 -> 0.34399059 | D35: =(D17-C17)/C17 -> 0.31070813 | E35: =(E17-D17)/D17 -> 0.14179513 | F35: =(F17-E17)/E17 -> 0.019077158
A36: Net Profit (PAT) Growth % | B36: - | C36: =(C20-B20)/B20 -> 0.23564973 | D36: =(D20-C20)/C20 -> 0.098789227 | E36: =(E20-D20)/D20 -> 0.043761806 | F36: =(F20-E20)/E20 -> 0.00038781402
A37: EPS Growth % | B37: - | C37: =(C21-B21)/B21 -> 0.15793873 | D37: =(D21-C21)/C21 -> 0.098675541 | E37: =(E21-D21)/D21 -> 0.043746379 | F37: =(F21-E21)/E21 -> 0.00031388864

Sheet Balance_Sheet
A1: RELIANCE INDUSTRIES - BALANCE SHEET
A2: All figures in ₹ Crores
A3: Particulars | B3: FY2021 | C3: FY2022 | D3: FY2023 | E3: FY2024 | F3: FY2025 | G3: 5Y CAGR
A4: EQUITY
A5: Equity Share Capital | B5: 6445 | C5: 6765 | D5: 6766 | E5: 6766 | F5: 13532 | G5: =(F5/B5)^(1/4)-1 -> 0.20374575
A6: Reserves | B6: 693727 | C6: 772720 | D6: 709106 | E6: 786715 | F6: 829668 | G6: =(F6/B6)^(1/4)-1 -> 0.045752558
A7: Total Equity | B7: =B6+B5 -> 700172 | C7: =C6+C5 -> 779485 | D7: =D6+D5 -> 715872 | E7: =E6+E5 -> 793481 | F7: =F6+F5 -> 843200
A9: LIABILITIES
A10: Borrowings | B10: 278962 | C10: 319158 | D10: 451664 | E10: 350719 | F10: 374313 | G10: =(F10/B10)^(1/4)-1 -> 0.07627305
A11: Other Liabilities | B11: 340931 | C11: 399979 | D11: 438346 | E11: 610848 | F11: 732200
A12: Total Liabilities | B12: =B11+B10 -> 619893 | C12: =C11+C10 -> 719137 | D12: =D11+D10 -> 890010 | E12: =E11+E10 -> 961567 | F12: =F11+F10 -> 1106513
A14: TOTAL EQUITY & LIABILITIES | B14: =B12+B7 -> 1320065 | C14: =C12+C7 -> 1498622 | D14: =D12+D7 -> 1605882 | E14: =E12+E7 -> 1755048 | F14: =F12+F7 -> 1949713
A16: ASSETS
A17: Net Block (Fixed Assets) | B17: 541258 | C17: 627798 | D17: 724805 | E17: 779985 | F17: 999393 | G17: =(F17/B17)^(1/4)-1 -> 0.16568979
A18: Capital Work in Progress | B18: 125953 | C18: 172506 | D18: 293752 | E18: 338855 | F18: 262358
A19: Investments | B19: 364828 | C19: 394264 | D19: 235560 | E19: 225672 | F19: 242381
A20: Other Assets | B20: 288026 | C20: 304054 | D20: 351765 | E20: 410536 | F20: 445581
A21: Total Assets | B21: =SUM(B17:B20) -> 1320065 | C21: =SUM(C17:C20) -> 1498622 | D21: =SUM(D17:D20) -> 1605882 | E21: =SUM(E17:E20) -> 1755048 | F21: =SUM(F17:F20) -> 1949713 | G21: =(F21/B21)^(1/4)-1 -> 0.10241177
A23: WORKING CAPITAL
A24: Working Capital | B24: -52905 | C24: -95925 | D24: -86581 | E24: -200312 | F24: -286619
A25: Debtors | B25: 19014 | C25: 23640 | D25: 28448 | E25: 31628 | F25: 42121
A26: Inventory | B26: 81672 | C26: 107778 | D26: 140008 | E26: 152770 | F26: 146062
A28: EFFICIENCY RATIOS
A29: Debtor Days | B29: 14.883135 | C29: 12.421096 | D29: 11.847977 | E29: 12.840593 | F29: 15.96785
A30: Inventory Turnover | B30: 5.7095088 | C30: 6.4454063 | D30: 6.2596137 | E30: 5.8849316 | F30: 6.5918583
A32: RETURNS
A33: Return on Equity (ROE) | B33: 0.070165616 | C33: 0.077878343 | D33: 0.093175875 | E33: 0.087741231 | F33: 0.08259962
A34: Return on Capital Employed (ROCE) | B34: 0.085957813 | C34: 0.09471565 | D34: 0.10064077 | E34: 0.11027038 | F34: 0.11033178

Sheet Cash_Flow
A1: RELIANCE INDUSTRIES - CASH FLOW STATEMENT
A2: All figures in ₹ Crores
A3: Particulars | B3: FY2021 | C3: FY2022 | D3: FY2023 | E3: FY2024 | F3: FY2025 | G3: 5Y CAGR
A4: OPERATING ACTIVITIES
A5: Cash from Operations | B5: 26958 | C5: 110654 | D5: 115032 | E5: 158788 | F5: 178703
A7: INVESTING ACTIVITIES
A8: Cash from Investing | B8: -142385 | C8: -109162 | D8: -93001 | E8: -113581 | F8: -137535
A10: FINANCING ACTIVITIES
A11: Cash from Financing | B11: 101904 | C11: 17289 | D11: 10455 | E11: -16646 | F11: -31891
A13: NET CASH FLOW
A14: Net Cash Flow | B14: -13523 | C14: 18781 | D14: 32486 | E14: 28561 | F14: 9277
A16: CASH FLOW ANALYSIS
A17: Opening Cash Balance | B17: 19839 | C17: -13523 | D17: 18781 | E17: 32486 | F17: 28561
A18: Closing Cash Balance | B18: -13523 | C18: 18781 | D18: 32486 | E18: 28561 | F18: 9277
A19: Change in Cash | B19: 6316 | C19: 5258 | D19: 51267 | E19: 61047 | F19: 37838
A21: KEY METRICS
A22: Free Cash Flow (FCF) | B22: =B5+B8 -> -115427 | C22: =C5+C8 -> 1492 | D22: =D5+D8 -> 22031 | E22: =E5+E8 -> 45207 | F22: =F5+F8 -> 41168
A23: FCF Margin % | B23: =Cash_Flow!B22/Income_Statement!B5 -> -0.24753435 | C23: =Cash_Flow!C22/Income_Statement!C5 -> 0.0021477731 | D23: =Cash_Flow!D22/Income_Statement!D5 -> 0.02513818 | E23: =Cash_Flow!E22/Income_Statement!E5 -> 0.05028358 | F23: =Cash_Flow!F22/Income_Statement!F5 -> 0.042757732
A24: Capex | B24: =ABS(B8) -> 142385 | C24: =ABS(C8) -> 109162 | D24: =ABS(D8) -> 93001 | E24: =ABS(E8) -> 113581 | F24: =ABS(F8) -> 137535
A25: Capex to Sales % | B25: =B24/Income_Statement!B5 -> 0.30534605 | C25: =C24/Income_Statement!C5 -> 0.15714156 | D25: =D24/Income_Statement!D5 -> 0.10611755 | E25: =E24/Income_Statement!E5 -> 0.12633573 | F25: =F24/Income_Statement!F5 -> 0.14284601
A26: Operating Cash Flow Margin % | B26: =B5/Income_Statement!B5 -> 0.057811699 | C26: =C5/Income_Statement!C5 -> 0.15928933 | D26: =D5/Income_Statement!D5 -> 0.13125573 | E26: =E5/Income_Statement!E5 -> 0.17661931 | F26: =F5/Income_Statement!F5 -> 0.18560375

Sheet Ratio_Analysis
A1: RELIANCE INDUSTRIES - RATIO ANALYSIS
A2: All figures in ₹ Crores unless stated
A3: Particulars | B3: FY2021 | C3: FY2022 | D3: FY2023 | E3: FY2024 | F3: FY2025 | G3: 5Y AVERAGE
A4: PROFITABILITY RATIOS
A5: Gross Profit Margin % | B5: =(Income_Statement!B5-Income_Statement!B10)/Income_Statement!B5 -> 0.17325496 | C5: =(Income_Statement!C5-Income_Statement!C10)/Income_Statement!C5 -> 0.1563052 | D5: =(Income_Statement!D5-Income_Statement!D10)/Income_Statement!D5 -> 0.16239006 | E5: =(Income_Statement!E5-Income_Statement!E10)/Income_Statement!E5 -> 0.18074593 | F5: =(Income_Statement!F5-Income_Statement!F10)/Income_Statement!F5 -> 0.17199269 | G5: =SUM(B5:F5)/5 -> 0.16893777
A6: Operating Profit Margin % | B6: =Income_Statement!B17 / Income_Statement!B5 -> 0.17325496 | C6: =Income_Statement!C17 / Income_Statement!C5 -> 0.1563052 | D6: =Income_Statement!D17 / Income_Statement!D5 -> 0.16239006 | E6: =Income_Statement!E17 / Income_Statement!E5 -> 0.18074593 | F6: =Income_Statement!F17 / Income_Statement!F5 -> 0.17199269 | G6: =SUM(B6:F6)/5 -> 0.16893777
A7: Net Profit Margin % | B7: =Income_Statement!B20/Income_Statement!B5 -> 0.10535548 | C7: =Income_Statement!C20/Income_Statement!C5 -> 0.087386439 | D7: =Income_Statement!D20/Income_Statement!D5 -> 0.07610943 | E7: =Income_Statement!E20/Income_Statement!E5 -> 0.077439182 | F7: =Income_Statement!F20/Income_Statement!F5 -> 0.072337509 | G7: =SUM(B7:F7)/5 -> 0.083725609
A8: EBITDA Margin % | B8: =Income_Statement!B18/Income_Statement!B5 -> 0.23023888 | C8: =Income_Statement!C18/Income_Statement!C5 -> 0.19917717 | D8: =Income_Statement!D18/Income_Statement!D5 -> 0.20837726 | E8: =Income_Statement!E18/Income_Statement!E5 -> 0.23728617 | F8: =Income_Statement!F18/Income_Statement!F5 -> 0.22718057 | G8: =SUM(B8:F8)/5 -> 0.22045201
A9: Return on Equity (ROE) % | B9: =Income_Statement!B20/(Balance_Sheet!B7+Balance_Sheet!B10) -> 0.050174951 | C9: =Income_Statement!C20/Balance_Sheet!C7 -> 0.077878343 | D9: =Income_Statement!D20/Balance_Sheet!D7 -> 0.093175875 | E9: =Income_Statement!E20/Balance_Sheet!E7 -> 0.087741231 | F9: =Income_Statement!F20/Balance_Sheet!F7 -> 0.08259962 | G9: =SUM(B9:F9)/5 -> 0.078314004
A10: Return on Capital Employed (ROCE) % | B10: =Income_Statement!B17/Balance_Sheet!B7 -> 0.11538593 | C10: =Income_Statement!C17/Balance_Sheet!C7 -> 0.13929838 | D10: =Income_Statement!D17/Balance_Sheet!D7 -> 0.1988037 | E10: =Income_Statement!E17/Balance_Sheet!E7 -> 0.20479129 | F10: =Income_Statement!F17/Balance_Sheet!F7 -> 0.19639231 | G10: =SUM(B10:F10)/5 -> 0.17093432
A11: Return on Assets (ROA) % | B11: =Balance_Sheet!B20/Balance_Sheet!B21 -> 0.21819077 | C11: =Balance_Sheet!C20/Balance_Sheet!C21 -> 0.20288905 | D11: =Balance_Sheet!D20/Balance_Sheet!D21 -> 0.21904785 | E11: =Balance_Sheet!E20/Balance_Sheet!E21 -> 0.23391725 | F11: =Balance_Sheet!F20/Balance_Sheet!F21 -> 0.22853671 | G11: =SUM(B11:F11)/5 -> 0.22051633
A13: LIQUIDITY RATIOS
A14: Working Capital | B14: =Balance_Sheet!B24 -> -52905 | C14: =Balance_Sheet!C24 -> -95925 | D14: =Balance_Sheet!D24 -> -86581 | E14: =Balance_Sheet!E24 -> -200312 | F14: =Balance_Sheet!F24 -> -286619
A15: Working Capital to Sales | B15: =-(Balance_Sheet!B24/Income_Statement!B5) -> 0.1134553 | C15: =-(Balance_Sheet!C24/Income_Statement!C5) -> 0.13808655 | D15: =-(Balance_Sheet!D24/Income_Statement!D5) -> 0.098792099 | E15: =-(Balance_Sheet!E24/Income_Statement!E5) -> 0.2228063 | F15: =-(Balance_Sheet!F24/Income_Statement!F5) -> 0.297687 | G15: =SUM(B15:F15)/5 -> 0.17416545
A16: Cash & Equivalents | B16: =Cash_Flow!B19 -> 6316 | C16: =Cash_Flow!C19 -> 5258 | D16: =Cash_Flow!D19 -> 51267 | E16: =Cash_Flow!E19 -> 61047 | F16: =Cash_Flow!F19 -> 37838
A18: LEVERAGE RATIOS
A19: Debt to Equity Ratio | B19: =Balance_Sheet!B10/Balance_Sheet!B7 -> 0.39841925 | C19: =Balance_Sheet!C10/Balance_Sheet!C7 -> 0.40944726 | D19: =Balance_Sheet!D10/Balance_Sheet!D7 -> 0.63092843 | E19: =Balance_Sheet!E10/Balance_Sheet!E7 -> 0.4420005 | F19: =Balance_Sheet!F10/Balance_Sheet!F7 -> 0.44391959 | G19: =SUM(B19:F19)/5 -> 0.46494301
A20: Debt to EBITDA | B20: =Balance_Sheet!B10/Income_Statement!B18 -> 2.5983309 | C20: =Balance_Sheet!C10/Income_Statement!C18 -> 2.3066716 | D20: =Balance_Sheet!D10/Income_Statement!D18 -> 2.4732314 | E20: =Balance_Sheet!E10/Income_Statement!E18 -> 1.644021 | F20: =Balance_Sheet!F10/Income_Statement!F18 -> 1.7112703 | G20: =SUM(B20:F20)/5 -> 2.146705
A21: Interest Coverage Ratio | B21: =Income_Statement!B17/Income_Statement!B11 -> 3.8128274 | C21: =Income_Statement!C17/Income_Statement!C11 -> 7.4452139 | D21: =Income_Statement!D17/Income_Statement!D11 -> 7.2718819 | E21: =Income_Statement!E17/Income_Statement!E11 -> 7.0290683 | F21: =Income_Statement!F17/Income_Statement!F11 -> 6.8234373 | G21: =SUM(B21:F21)/5 -> 6.4764858
A23: EFFICIENCY RATIOS
A24: Asset Turnover Ratio | B24: =Income_Statement!B5/Balance_Sheet!B21 -> 0.35324548 | C24: =Income_Statement!C5/Balance_Sheet!C21 -> 0.46354117 | D24: =Income_Statement!D5/Balance_Sheet!D21 -> 0.54574122 | E24: =Income_Statement!E5/Balance_Sheet!E21 -> 0.51226006 | F24: =Income_Statement!F5/Balance_Sheet!F21 -> 0.49382653 | G24: =SUM(B24:F24)/5 -> 0.47372289
A25: Inventory Turnover | B25: =Balance_Sheet!B26 -> 81672 | C25: =Balance_Sheet!C26 -> 107778 | D25: =Balance_Sheet!D26 -> 140008 | E25: =Balance_Sheet!E26 -> 152770 | F25: =Balance_Sheet!F26 -> 146062
A26: Debtor Days | B26: =Balance_Sheet!B25 -> 19014 | C26: =Balance_Sheet!C25 -> 23640 | D26: =Balance_Sheet!D25 -> 28448 | E26: =Balance_Sheet!E25 -> 31628 | F26: =Balance_Sheet!F25 -> 42121
A28: VALUATION RATIOS
A29: Price to Earnings (P/E) | B29: =Income_Statement!B30 -> 23.711773 | C29: =Income_Statement!C30 -> 26.935011 | D29: =Income_Statement!D30 -> 21.690046 | E29: =Income_Statement!E30 -> 28.878687 | F29: =Income_Statement!F30 -> 24.774815
A30: Price to Book (P/B) | B30: =Income_Statement!B31/Balance_Sheet!B7 -> 1.774122 | C30: =Income_Statement!C31/Balance_Sheet!C7 -> 2.0961347 | D30: =Income_Statement!D31/Balance_Sheet!D7 -> 2.0193162 | E30: =Income_Statement!E31/Balance_Sheet!E7 -> 2.5317168 | F30: =Income_Statement!F31/Balance_Sheet!F7 -> 2.0445152
A31: EV/EBITDA | B31: =(Income_Statement!B31+Balance_Sheet!B10+Cash_Flow!B18)/Income_Statement!B18 -> 14.042488 | C31: =(Income_Statement!C31+Balance_Sheet!C10+Cash_Flow!C18)/Income_Statement!C18 -> 14.251241 | D31: =(Income_Statement!D31+Balance_Sheet!D10+Cash_Flow!D18)/Income_Statement!D18 -> 10.566813 | E31: =(Income_Statement!E31+Balance_Sheet!E10+Cash_Flow!E18)/Income_Statement!E18 -> 11.194624 | F31: =(Income_Statement!F31+Balance_Sheet!F10+Cash_Flow!F18)/Income_Statement!F18 -> 9.6351057
A32: Market Cap to Sales | B32: =Income_Statement!B31/Income_Statement!B5 -> 2.66389 | C32: =Income_Statement!C31/Income_Statement!C5 -> 2.3520498 | D32: =Income_Statement!D31/Income_Statement!D5 -> 1.6494506 | E32: =Income_Statement!E31/Income_Statement!E5 -> 2.2344578 | F32: =Income_Statement!F31/Income_Statement!F5 -> 1.7905062

Sheet DashBoard
B1: RELIANCE INDUSTRIES LIMITED - FINANCIAL ANALYSIS DASHBOARD FY2021-FY2025
B2: Financial Model | Excel | Data Source: Screener.in & Annual Reports
B4: FY2025 Revenue | D4: FY2025 Net Profit | F4: 4Y Revenue CAGR | H4: FY2025 ROCE
B5: =Income_Statement!F5 -> 962820 | D5: =Income_Statement!F20 -> 69648 | F5: =Income_Statement!G5 -> 0.19872149 | H5: =Ratio_Analysis!F10 -> 0.19639231
V6: FY2021 | W6: FY2022 | X6: FY2023 | Y6: FY2024 | Z6: FY2025
U7: Revenue | V7: =Income_Statement!B5 -> 466307 | W7: =Income_Statement!C5 -> 694673 | X7: =Income_Statement!D5 -> 876396 | Y7: =Income_Statement!E5 -> 899041 | Z7: =Income_Statement!F5 -> 962820
U8: EBITDA | V8: =Income_Statement!B18 -> 107362 | W8: =Income_Statement!C18 -> 138363 | X8: =Income_Statement!D18 -> 182621 | Y8: =Income_Statement!E18 -> 213330 | Z8: =Income_Statement!F18 -> 218734
U9: Net Profit | V9: =Income_Statement!B20 -> 49128 | W9: =Income_Statement!C20 -> 60705 | X9: =Income_Statement!D20 -> 66702 | Y9: =Income_Statement!E20 -> 69621 | Z9: =Income_Statement!F20 -> 69648
V11: FY2021 | W11: FY2022 | X11: FY2023 | Y11: FY2024 | Z11: FY2025
U12: OPM % | V12: =Income_Statement!B24 -> 0.17325496 | W12: =Income_Statement!C24 -> 0.1563052 | X12: =Income_Statement!D24 -> 0.16239006 | Y12: =Income_Statement!E24 -> 0.18074593 | Z12: =Income_Statement!F24 -> 0.17199269
U13: Net Margin % | V13: =Income_Statement!B25 -> 0.10051991 | W13: =Income_Statement!C25 -> 0.084988513 | X13: =Income_Statement!D25 -> 0.075079692 | Y13: =Income_Statement!E25 -> 0.076102414 | Z13: =Income_Statement!F25 -> 0.071022716
U14: EBITDA Margin % | V14: =Ratio_Analysis!B8 -> 0.23023888 | W14: =Ratio_Analysis!C8 -> 0.19917717 | X14: =Ratio_Analysis!D8 -> 0.20837726 | Y14: =Ratio_Analysis!E8 -> 0.23728617 | Z14: =Ratio_Analysis!F8 -> 0.22718057
U16: Category | V16: Value | Y16: FY2021 | Z16: FY2022 | AA16: FY2023 | AB16: FY2024 | AC16: FY2025
U17: Operating CF | V17: =Cash_Flow!F5 -> 178703 | X17: ROE % | Y17: =Ratio_Analysis!B9 -> 0.050174951 | Z17: =Ratio_Analysis!C9 -> 0.077878343 | AA17: =Ratio_Analysis!D9 -> 0.093175875 | AB17: =Ratio_Analysis!E9 -> 0.087741231 | AC17: =Ratio_Analysis!F9 -> 0.08259962
U18: Investing CF | V18: =Cash_Flow!F8 -> -137535 | X18: ROCE % | Y18: =Ratio_Analysis!B10 -> 0.11538593 | Z18: =Ratio_Analysis!C10 -> 0.13929838 | AA18: =Ratio_Analysis!D10 -> 0.1988037 | AB18: =Ratio_Analysis!E10 -> 0.20479129 | AC18: =Ratio_Analysis!F10 -> 0.19639231
U19: Financing CF | V19: =Cash_Flow!F11 -> -31891 | X19: ROA % | Y19: =Ratio_Analysis!B11 -> 0.21819077 | Z19: =Ratio_Analysis!C11 -> 0.20288905 | AA19: =Ratio_Analysis!D11 -> 0.21904785 | AB19: =Ratio_Analysis!E11 -> 0.23391725 | AC19: =Ratio_Analysis!F11 -> 0.22853671
U20: Net Cash Flow | V20: =Cash_Flow!F14 -> 9277
B34: Reliance Industries Annual Reports | Built by Hardik Parmar | For Educational & Portfolio Purposes Only | March 2026

Sheet Key_Findings
A1: RELIANCE INDUSTRIES — KEY FINDINGS\
A2: Financial Analysis FY2021-FY2025 | All figures in ₹ Crores
A4: COMPANY SNAPSHOT
A5: Sector | B5: Oil & Gas, Telecom, Retail, New Energy
A6: Market Cap (FY2025) | B6: =Income_Statement!F31 -> 1723935.2
A7: Revenue (FY2025) | B7: =Income_Statement!F7 -> 980644
A8: Net Profit (FY2025) | B8: =Income_Statement!F20 -> 69648
A9: Employees | B9: ~2,36,334
A10: Founded | B10: 1966
A11: Chairman | B11: Mukesh Ambani
A13: KEY FINANCIAL HIGHLIGHTS
A14: Highlight 1 | B14: Revenue grew at 19.8% CAGR from ₹4,66,307 Cr (FY2021) to ₹9,62,820 Cr (FY2025) — doubling in 4 years
A15: Highlight 2 | B15: EBITDA expanded from ₹1,07,362 Cr to ₹2,18,734 Cr. A 4Y CAGR of ~19% reflecting strong operational growth
A16: Highlight 3 | B16: Operating Cash Flow margin expanded from 5.8% to 18.6%, core business cash generation tripled over 5 years
A17: Highlight 4 | B17: ROCE improved from 9% to 11% despite heavy capex, capital deployed productively across all segments
A18: Highlight 5 | B18: FCF turned positive from FY2022 onwards after heavy investment phase. FY2025 FCF of ₹41,168 Cr signals investment maturity
A20: STRENGTHS
A21: Strength 1 | B21: Unmatched scale - largest Indian company by revenue and market cap with diversified business across 4 segments
A22: Strength 2 | B22: Negative working capital advantage - retail and telecom businesses collect cash before paying suppliers providing free funding of ₹2,86,619 Cr
A23: Strength 3 | B23: Strong cash generation - Operating CF grew 6.6x from ₹26,958 Cr to ₹1,78,703 Cr over 5 years
A25: RISKS & CONCERNS
A26: Risk 1 | B26: Margin compression - OPM declined from 17.3% to 17.2% with significant intra-period volatility driven by commodity price cycles in O2C segment
A27: Risk 2 | B27: Rising debt - Borrowings increased from ₹2,78,962 Cr to ₹3,74,313 Cr, interest costs rising alongside capex
A28: Risk 3 | B28: Regulatory risk - Jio operates in heavily regulated telecom sector subject to spectrum pricing and interconnect policy changes
A30: INVESTMENT THESIS
A31: Reliance Industries represents a unique convergence of energy, digital and consumer businesses under one roof. The company is transitioning from a commodity-driven O2C business to high-margin consumer-facing segments (Jio + Retail) while simultaneously investing in New Energy for long-term growth. With improving FCF, rising ROCE and strong cash generation. Reliance is well positioned for sustainable value creation over the next decade. Key risks include margin volatility in O2C and rising debt levels from ongoing capex commitments.
